{
    "paper_id": "improving_classification_neural_networks_by_using_absolute_activation_function_mnistlenet-5_example",
    "header": {
        "generated_with": "S2ORC 1.0.0",
        "date_generated": "2026-04-26T04:34:56.401432Z"
    },
    "title": "Improving Classification Neural Networks by using Absolute activation function (MNIST/LeNET-5 example)",
    "authors": [
        {
            "first": "Oleg",
            "middle": [
                "I"
            ],
            "last": "Berngardt",
            "suffix": "",
            "affiliation": {},
            "email": ""
        }
    ],
    "year": "",
    "venue": null,
    "identifiers": {},
    "abstract": "The paper discusses the use of the Absolute activation function in classification neural networks. An examples are shown of using this activation function in simple and more complex problems. Using as a baseline LeNet-5 network for solving the MNIST problem, the efficiency of Absolute activation function is shown in comparison with the use of Tanh, ReLU and SeLU activations. It is shown that in deep networks Absolute activation does not cause vanishing and exploding gradients, and therefore Absolute activation can be used in both simple and deep neural networks. Due to high volatility of training networks with Absolute activation, a special modification of ADAM training algorithm is used, that estimates lower bound of accuracy at any test dataset using validation dataset analysis at each training epoch, and uses this value to stop/decrease learning rate, and reinitializes ADAM algorithm between these steps. It is shown that solving the MNIST problem with the LeNet-like architectures based on Absolute activation allows to significantly reduce the number of trained parameters in the neural network with improving the prediction accuracy.",
    "pdf_parse": {
        "paper_id": "improving_classification_neural_networks_by_using_absolute_activation_function_mnistlenet-5_example",
        "_pdf_hash": "",
        "abstract": [
            {
                "text": "The paper discusses the use of the Absolute activation function in classification neural networks. An examples are shown of using this activation function in simple and more complex problems. Using as a baseline LeNet-5 network for solving the MNIST problem, the efficiency of Absolute activation function is shown in comparison with the use of Tanh, ReLU and SeLU activations. It is shown that in deep networks Absolute activation does not cause vanishing and exploding gradients, and therefore Absolute activation can be used in both simple and deep neural networks. Due to high volatility of training networks with Absolute activation, a special modification of ADAM training algorithm is used, that estimates lower bound of accuracy at any test dataset using validation dataset analysis at each training epoch, and uses this value to stop/decrease learning rate, and reinitializes ADAM algorithm between these steps. It is shown that solving the MNIST problem with the LeNet-like architectures based on Absolute activation allows to significantly reduce the number of trained parameters in the neural network with improving the prediction accuracy.",
                "cite_spans": [],
                "ref_spans": [],
                "eq_spans": [],
                "section": "Abstract",
                "sec_num": null
            }
        ],
        "body_text": [
            {
                "text": "Many tasks have recently been effectively solved by neural networks. Deep neural networks are the most actively studied, the intensive progress in their development is associated with successful solution of the problem of vanishing and exploding gradients in deep networks.",
                "cite_spans": [],
                "ref_spans": [],
                "eq_spans": [],
                "section": "Introduction and basic idea",
                "sec_num": "1"
            },
            {
                "text": "In practical use, the problem often arises of constructing from already trained deep network a smaller network allowing one to successfully solve the problem with similar quility [Hinton et al.(2015) ]. The main theoretical basis for the possibility of creating small networks are the theorems of Kolmogorov-Arnold [Kolmogorov(1957) , Arnold(1963) ], Cybenko [Cybenko(1989) ], Funahashi [Funahashi(1989) ], and Hornik [Hornik et al.(1989) , Hornik(1991) ] (also known as the universal approximation theorem) .",
                "cite_spans": [
                    {
                        "start": 179,
                        "end": 199,
                        "text": "[Hinton et al.(2015)",
                        "ref_id": "BIBREF0"
                    },
                    {
                        "start": 297,
                        "end": 332,
                        "text": "Kolmogorov-Arnold [Kolmogorov(1957)",
                        "ref_id": null
                    },
                    {
                        "start": 335,
                        "end": 347,
                        "text": "Arnold(1963)",
                        "ref_id": "BIBREF2"
                    },
                    {
                        "start": 351,
                        "end": 373,
                        "text": "Cybenko [Cybenko(1989)",
                        "ref_id": "BIBREF3"
                    },
                    {
                        "start": 387,
                        "end": 403,
                        "text": "[Funahashi(1989)",
                        "ref_id": "BIBREF4"
                    },
                    {
                        "start": 418,
                        "end": 438,
                        "text": "[Hornik et al.(1989)",
                        "ref_id": "BIBREF5"
                    },
                    {
                        "start": 441,
                        "end": 453,
                        "text": "Hornik(1991)",
                        "ref_id": "BIBREF6"
                    }
                ],
                "ref_spans": [],
                "eq_spans": [],
                "section": "Introduction and basic idea",
                "sec_num": "1"
            },
            {
                "text": "1",
                "cite_spans": [],
                "ref_spans": [],
                "eq_spans": [],
                "section": "Introduction and basic idea",
                "sec_num": "1"
            },
            {
                "text": "In accordance with the Kolmogorov-Arnold theorem, the approximation of an unknown function of N variables can be represented as:",
                "cite_spans": [],
                "ref_spans": [],
                "eq_spans": [],
                "section": "Introduction and basic idea",
                "sec_num": "1"
            },
            {
                "text": "EQUATION",
                "cite_spans": [],
                "ref_spans": [],
                "eq_spans": [
                    {
                        "start": 0,
                        "end": 8,
                        "text": "EQUATION",
                        "ref_id": "EQREF",
                        "raw_str": "f ( - \u2192 x ) = 2N q=0 \u03a6 q N p=1 \u03c6 q,p (x p ) (",
                        "eq_num": "1"
                    }
                ],
                "section": "Introduction and basic idea",
                "sec_num": "1"
            },
            {
                "text": ")",
                "cite_spans": [],
                "ref_spans": [],
                "eq_spans": [],
                "section": "Introduction and basic idea",
                "sec_num": "1"
            },
            {
                "text": "The theorem is not constructive, and proves the existence of optimal functions of one argument \u03a6 q (x) , \u03c6 q,p (x) that provide such an approximation, but does not specify their specific shape.",
                "cite_spans": [],
                "ref_spans": [],
                "eq_spans": [],
                "section": "Introduction and basic idea",
                "sec_num": "1"
            },
            {
                "text": "The theorems [Cybenko(1989) , Funahashi(1989) , Hornik et al.(1989) , Hornik(1991) , Sonoda and Murata(2017) ] specify the types of these functions and prove the possibility of using various functions \u03a6 q (x) , \u03c6 q,p (x). Thus, theoretically, most of the practical problems should be solved by a neural network with one hidden layer by choosing correct functions \u03a6 q (x) , \u03c6 q,p (x).",
                "cite_spans": [
                    {
                        "start": 13,
                        "end": 27,
                        "text": "[Cybenko(1989)",
                        "ref_id": "BIBREF3"
                    },
                    {
                        "start": 30,
                        "end": 45,
                        "text": "Funahashi(1989)",
                        "ref_id": "BIBREF4"
                    },
                    {
                        "start": 48,
                        "end": 67,
                        "text": "Hornik et al.(1989)",
                        "ref_id": "BIBREF5"
                    },
                    {
                        "start": 70,
                        "end": 82,
                        "text": "Hornik(1991)",
                        "ref_id": "BIBREF6"
                    },
                    {
                        "start": 85,
                        "end": 108,
                        "text": "Sonoda and Murata(2017)",
                        "ref_id": "BIBREF7"
                    }
                ],
                "ref_spans": [],
                "eq_spans": [],
                "section": "Introduction and basic idea",
                "sec_num": "1"
            },
            {
                "text": "Traditionally, however, for large input vectors this hidden layer size and number of unknown functions becomes as huge as O(N 2 ), where N is dimension of input vector. Therefore the solution of many problems is reduced to the construction of neural networks with a larger number of hidden layers, and smaller number of neurons in each layer ('thin networks'), that efficiently decrease number of unknown (trained) parameters. However, there are still problems in which the use of a large number of hidden layers is not required, and the problem can be solved with a simpler network.",
                "cite_spans": [],
                "ref_spans": [],
                "eq_spans": [],
                "section": "Introduction and basic idea",
                "sec_num": "1"
            },
            {
                "text": "The simplest form of the function \u03c6 q,p is linear:",
                "cite_spans": [],
                "ref_spans": [],
                "eq_spans": [],
                "section": "Introduction and basic idea",
                "sec_num": "1"
            },
            {
                "text": "EQUATION",
                "cite_spans": [],
                "ref_spans": [],
                "eq_spans": [
                    {
                        "start": 0,
                        "end": 8,
                        "text": "EQUATION",
                        "ref_id": "EQREF",
                        "raw_str": "\u03c6 q,p (x) = A p,q x + B p,q",
                        "eq_num": "(2)"
                    }
                ],
                "section": "Introduction and basic idea",
                "sec_num": "1"
            },
            {
                "text": "and the \u03a6 q function is the neuron activation function. This allows one to build neural networks with one hidden layer to solve some problems by choosing corresponding activation function and fitting coefficients A p,q , B p,q .",
                "cite_spans": [],
                "ref_spans": [],
                "eq_spans": [],
                "section": "Introduction and basic idea",
                "sec_num": "1"
            },
            {
                "text": "A difficult task is to choose the function \u03a6 q -the activation function of the hidden layer. The theorem [Hornik(1991) ] proves that as this function one can use a sufficiently arbitrary function -continuous and bounded. However even non-bounded functions can be used, for example widely used ReLU [Agarap(2018) ], that satisfy less strong conditions [Sonoda and Murata(2017) ] and also could be used in universal approximators (networks) .",
                "cite_spans": [
                    {
                        "start": 105,
                        "end": 118,
                        "text": "[Hornik(1991)",
                        "ref_id": "BIBREF6"
                    },
                    {
                        "start": 298,
                        "end": 311,
                        "text": "[Agarap(2018)",
                        "ref_id": "BIBREF8"
                    },
                    {
                        "start": 351,
                        "end": 375,
                        "text": "[Sonoda and Murata(2017)",
                        "ref_id": "BIBREF7"
                    },
                    {
                        "start": 428,
                        "end": 438,
                        "text": "(networks)",
                        "ref_id": null
                    }
                ],
                "ref_spans": [],
                "eq_spans": [],
                "section": "Introduction and basic idea",
                "sec_num": "1"
            },
            {
                "text": "The only problem is to find the coefficients A p,q , B p,q . In modern time this problem is solved by gradient descent methods. Modern experience in building deep neural networks shows that in order to avoid vanishing and exploding gradients [Bengio et al.(1994) ] when searching for optimal network coefficients using the gradient descent method, only some activation functions are beneficial. This greatly limits the activation functions suitable for building deep neural networks. For optimal activation functions, the derivative of the function should be as close as possible to 1. This is one of the reasons for replacing Sigmoid (logistic function) with Tanh (hyperbolic tangent) in the LeNet [Lecun et al.(1998) ] network, replacing Tanh with ReLU (Rectified Linear Unit) in the AlexNet [Krizhevsky et al.(2017) ] network, and the emergence of Residual blocks and ResNet[He et al.(2015) ] networks, that are widely used today.",
                "cite_spans": [
                    {
                        "start": 242,
                        "end": 262,
                        "text": "[Bengio et al.(1994)",
                        "ref_id": "BIBREF9"
                    },
                    {
                        "start": 699,
                        "end": 718,
                        "text": "[Lecun et al.(1998)",
                        "ref_id": "BIBREF9"
                    },
                    {
                        "start": 794,
                        "end": 818,
                        "text": "[Krizhevsky et al.(2017)",
                        "ref_id": "BIBREF10"
                    },
                    {
                        "start": 851,
                        "end": 893,
                        "text": "Residual blocks and ResNet[He et al.(2015)",
                        "ref_id": null
                    }
                ],
                "ref_spans": [],
                "eq_spans": [],
                "section": "Introduction and basic idea",
                "sec_num": "1"
            },
            {
                "text": "Therefore, the requirement that the derivative of the activation function be close to 1 is a very important requirement when choosing activation functions for deep neural networks. An ideal function that satisfies this condition is linear. This function is not useful, since it will not allow effective building deep networks -the superposition of layers with linear activation functions is equivalent to a single layer. Thus, we face with a contradiction, which is usually resolved by using the ReLU and similar right-hand-linear functions (SeLU, SWISH, MISH, APTx, etc.) or Residual blocks.",
                "cite_spans": [],
                "ref_spans": [],
                "eq_spans": [],
                "section": "Introduction and basic idea",
                "sec_num": "1"
            },
            {
                "text": "However, this contradiction is apparent: in order for the gradient to do not vanish or explode, a slightly different condition should be met. Namely, not the derivative, but the modulus of the derivative of the activation function must be equal to 1. This property is possessed not only by a linear function, but also by many other real-valued functions whose derivative modulus are equal to 1 almost everywhere. We can classify these functions by the number of points where their differential is not defined. The simplest function with none of these points is linear, and the function with single point is absolute value (module). So we can use absolute value function as an activation function (Absolute activation function, Abs), and \u03a6 q becomes:",
                "cite_spans": [],
                "ref_spans": [],
                "eq_spans": [],
                "section": "Introduction and basic idea",
                "sec_num": "1"
            },
            {
                "text": "EQUATION",
                "cite_spans": [],
                "ref_spans": [],
                "eq_spans": [
                    {
                        "start": 0,
                        "end": 8,
                        "text": "EQUATION",
                        "ref_id": "EQREF",
                        "raw_str": "\u03a6 q (y) = W q |y| (",
                        "eq_num": "3"
                    }
                ],
                "section": "Introduction and basic idea",
                "sec_num": "1"
            },
            {
                "text": ")",
                "cite_spans": [],
                "ref_spans": [],
                "eq_spans": [],
                "section": "Introduction and basic idea",
                "sec_num": "1"
            },
            {
                "text": "It should be noted that most of the popular activation functions (Sigmoid, Tanh, ReLU, SeLU, LeakyReLU, etc.) are monotonically nondecreasing. Absolute activation function Abs differs significantly from them -it is nonmonotone, but continuous, like SWISH, MISH and APTx functions [Kumar(2022) ]. The Absolute activation function already mentioned by researchers [Karnewar(2018) , Apicella et al.(2021) ], but its efficiency has not been demonstrated in details. The Absolute activation function satisfy conditions of [Sonoda and Murata(2017) ] and therefore could be used in universal approximators (neural networks).",
                "cite_spans": [
                    {
                        "start": 280,
                        "end": 292,
                        "text": "[Kumar(2022)",
                        "ref_id": "BIBREF11"
                    },
                    {
                        "start": 362,
                        "end": 377,
                        "text": "[Karnewar(2018)",
                        "ref_id": "BIBREF12"
                    },
                    {
                        "start": 380,
                        "end": 401,
                        "text": "Apicella et al.(2021)",
                        "ref_id": "BIBREF13"
                    },
                    {
                        "start": 517,
                        "end": 541,
                        "text": "[Sonoda and Murata(2017)",
                        "ref_id": "BIBREF7"
                    }
                ],
                "ref_spans": [],
                "eq_spans": [],
                "section": "Introduction and basic idea",
                "sec_num": "1"
            },
            {
                "text": "A neural network with one hidden layer with an N-dimensional input vector and Absolute activation will implement the operation:",
                "cite_spans": [],
                "ref_spans": [],
                "eq_spans": [],
                "section": "Introduction and basic idea",
                "sec_num": "1"
            },
            {
                "text": "EQUATION",
                "cite_spans": [],
                "ref_spans": [],
                "eq_spans": [
                    {
                        "start": 0,
                        "end": 8,
                        "text": "EQUATION",
                        "ref_id": "EQREF",
                        "raw_str": "f ( - \u2192 x ) = 2N q=0 W q N p=1 (A p,q x p + B p,q ) (",
                        "eq_num": "4"
                    }
                ],
                "section": "Introduction and basic idea",
                "sec_num": "1"
            },
            {
                "text": ")",
                "cite_spans": [],
                "ref_spans": [],
                "eq_spans": [],
                "section": "Introduction and basic idea",
                "sec_num": "1"
            },
            {
                "text": "It can be seen from the eq.( 4) that the network is implemented by two layers of neurons -the hidden fully connected layer with an Absolute activation function (Abs, \u03d5(y) = |y|) and with the number of neurons 2N+1, where N is the dimension of the input vector. The decision layer is standard for the given problem: with a linear activation function in the case of solving the approximation problem, as in (4) or with a Softmax function in the case of solving the classification problem:",
                "cite_spans": [],
                "ref_spans": [],
                "eq_spans": [],
                "section": "Introduction and basic idea",
                "sec_num": "1"
            },
            {
                "text": "EQUATION",
                "cite_spans": [],
                "ref_spans": [],
                "eq_spans": [
                    {
                        "start": 0,
                        "end": 8,
                        "text": "EQUATION",
                        "ref_id": "EQREF",
                        "raw_str": "f c ( - \u2192 x ) = Sof tmax c 2N q=0 W q,c N p=1 (A p,q x p + B p,q ) (",
                        "eq_num": "5"
                    }
                ],
                "section": "Introduction and basic idea",
                "sec_num": "1"
            },
            {
                "text": ")",
                "cite_spans": [],
                "ref_spans": [],
                "eq_spans": [],
                "section": "Introduction and basic idea",
                "sec_num": "1"
            },
            {
                "text": "where c is the class number and W q are the coefficients of the decision layer.",
                "cite_spans": [],
                "ref_spans": [],
                "eq_spans": [],
                "section": "Introduction and basic idea",
                "sec_num": "1"
            },
            {
                "text": "Let us demonstrate the possibility of using the Absolute activation function for effective solving simple classification problems. Let us compare three networks: a fully-connected network with single hidden layer with ReLU activations, a fully-connected network with two hidden layers with ReLU activations, and a fully-connected network with single hidden layer with Abs activations. We will use two-dimensional input vectors (N=2). The three synthetic problems of twoclass classification were solved: a) linear separation, b) \"cross\" type separation, c) circular area separation. These tasks are shown in Fig. 1 .",
                "cite_spans": [],
                "ref_spans": [
                    {
                        "start": 612,
                        "end": 613,
                        "text": "1",
                        "ref_id": "FIGREF0"
                    }
                ],
                "eq_spans": [],
                "section": "Simplest 2D classification problems",
                "sec_num": "2"
            },
            {
                "text": "In accordance with (4) and the Kolmogorov-Arnold theorem (1), we choose the number of neurons in each layer equal to 2N+1=5. The number of training epochs is 1000, loss function is cross-entropy, the optimum search method is ADAM [Kingma and Ba(2014) ] with learning rate 10 -3 . The first network has two hidden layers and 57 unknown parameters, the second and third networks have one hidden layer and 27 unknown parameters.",
                "cite_spans": [
                    {
                        "start": 230,
                        "end": 250,
                        "text": "[Kingma and Ba(2014)",
                        "ref_id": "BIBREF13"
                    }
                ],
                "ref_spans": [],
                "eq_spans": [],
                "section": "Simplest 2D classification problems",
                "sec_num": "2"
            },
            {
                "text": "The architectures of the studied networks and training processes are shown in Fig. 2 . Fig. 2 also shows the results of training the networks on these synthetic test datasets (A-C).",
                "cite_spans": [],
                "ref_spans": [
                    {
                        "start": 83,
                        "end": 84,
                        "text": "2",
                        "ref_id": null
                    },
                    {
                        "start": 92,
                        "end": 93,
                        "text": "2",
                        "ref_id": null
                    }
                ],
                "eq_spans": [],
                "section": "Simplest 2D classification problems",
                "sec_num": "2"
            },
            {
                "text": "It should be noted that the solution of datasets (B-C) by a network with single hidden ReLU layer looks unstable. In the most cases it predicts accurate classification, but in some cases -an inaccurate one (see Fig. 2B for datasets B and C). Experiments shows, that for dataset B inaccurate training (final accuracy is less than 0.8) is about 9% of all cases, for dataset C inaccurate training is about 16% of all cases. For two hidden layer ReLU network inaccurate training probability is about 3% of B-C cases (possibly due to small number of training epochs), for single hidden layer Abs network there are no inaccurate runs.",
                "cite_spans": [],
                "ref_spans": [
                    {
                        "start": 216,
                        "end": 218,
                        "text": "2B",
                        "ref_id": null
                    }
                ],
                "eq_spans": [],
                "section": "Simplest 2D classification problems",
                "sec_num": "2"
            },
            {
                "text": "This demonstrates a dependence of the single fully-connected hidden layer ReLU network on the initial conditions (initial coefficients values), and weaker dependence of the single fully-connected hidden layer Abs network results on initial conditions.",
                "cite_spans": [],
                "ref_spans": [],
                "eq_spans": [],
                "section": "Simplest 2D classification problems",
                "sec_num": "2"
            },
            {
                "text": "Fig. 2 shows that the neural network with single hidden layer and Abs activations is no less efficient than the network with single ReLU hidden layer, but less efficient than the network with two ReLU hidden layers. At the same time, it has the same number of free parameters as the network with one hidden ReLU layer and is less dependent on initial conditions during training. So from the first view Abs activation function can be effectively used in classification Figure 2: The architecture of the studied simple networks: a) two hidden layers with ReLU activations, b) single hidden layer with ReLU activations c) single hidden layer with Abs activations. Results of training three networks on datasets (A-C, as shown in Fig.1). For each dataset, the dependence of the loss function on the training epoch on the training and validation datasets is shown.",
                "cite_spans": [],
                "ref_spans": [
                    {
                        "start": 5,
                        "end": 6,
                        "text": "2",
                        "ref_id": null
                    }
                ],
                "eq_spans": [],
                "section": "Simplest 2D classification problems",
                "sec_num": "2"
            },
            {
                "text": "networks and may improve their efficiency. Let us study the use of Absolute activation in more complex classification problems.",
                "cite_spans": [],
                "ref_spans": [],
                "eq_spans": [],
                "section": "Simplest 2D classification problems",
                "sec_num": "2"
            },
            {
                "text": "3 LeNet-kind solution of MNIST problem",
                "cite_spans": [],
                "ref_spans": [],
                "eq_spans": [],
                "section": "Simplest 2D classification problems",
                "sec_num": "2"
            },
            {
                "text": "Let us consider the solution of the MNIST problem -the task of classifying handwritten digital characters into 10 classes [Simard et al.(2003) ].",
                "cite_spans": [
                    {
                        "start": 122,
                        "end": 142,
                        "text": "[Simard et al.(2003)",
                        "ref_id": "BIBREF14"
                    }
                ],
                "ref_spans": [],
                "eq_spans": [],
                "section": "Preliminary analysis",
                "sec_num": "3.1"
            },
            {
                "text": "When solving the MNIST problem, the LeNet-5 [Lecun et al.(1998) ] network was frequently used as a baseline solution, which is quite compact and fast. To demonstrate the effectiveness of Absolute activation, the network was analyzed in two versions -in its standard variant (with Tanh activation functions, LeNet-5) and its modernization, obtained from LeNet-5 by replacing all the activation functions by Abs (referred as LeNet+Abs).",
                "cite_spans": [
                    {
                        "start": 44,
                        "end": 63,
                        "text": "[Lecun et al.(1998)",
                        "ref_id": "BIBREF9"
                    }
                ],
                "ref_spans": [],
                "eq_spans": [],
                "section": "Preliminary analysis",
                "sec_num": "3.1"
            },
            {
                "text": "Both networks have 368,426 free parameters, network architectures are similar and shown in Fig. 3 . Significant differences are highlighted in bold. There are also more efficient networks exist for solving the MNIST problem, for example listed in [Apicella et al.(2021) ], but usualy they contain a larger number of free parameters (for example as much as 2,888,000, as in [Simard et al.(2003) ]). Therefore, to demonstrate the effectiveness of the Absolute activation function, we will use a relatively simple LeNet-5 as baseline solution.",
                "cite_spans": [
                    {
                        "start": 247,
                        "end": 269,
                        "text": "[Apicella et al.(2021)",
                        "ref_id": "BIBREF13"
                    },
                    {
                        "start": 373,
                        "end": 393,
                        "text": "[Simard et al.(2003)",
                        "ref_id": "BIBREF14"
                    }
                ],
                "ref_spans": [
                    {
                        "start": 96,
                        "end": 97,
                        "text": "3",
                        "ref_id": "FIGREF1"
                    }
                ],
                "eq_spans": [],
                "section": "Preliminary analysis",
                "sec_num": "3.1"
            },
            {
                "text": "Fig. 3 shows the dependencies of the loss function and accuracy of both networks after 100 training epochs on identical MNIST training and validation datasets (80% training data followed by 20% of validation data). Optimization algorithm is ADAM with batchsize 128 and learning rate 10 -3 .",
                "cite_spans": [],
                "ref_spans": [
                    {
                        "start": 5,
                        "end": 6,
                        "text": "3",
                        "ref_id": "FIGREF1"
                    }
                ],
                "eq_spans": [],
                "section": "Preliminary analysis",
                "sec_num": "3.1"
            },
            {
                "text": "It can be seen from Fig. 3 that the resulting accuracy of the LeNet+Abs network looks higher than the accuracy of the standard LeNet-5, and with an accurate training stop, it should provide the better accuracy and the smaller value of the loss function on the validation dataset, than standard LeNet-5 does. Thus, using the Abs activation function in this problem at first view is more profitable than the use of Tanh activations due to the greater accuracy achieved.",
                "cite_spans": [],
                "ref_spans": [
                    {
                        "start": 25,
                        "end": 26,
                        "text": "3",
                        "ref_id": "FIGREF1"
                    }
                ],
                "eq_spans": [],
                "section": "Preliminary analysis",
                "sec_num": "3.1"
            },
            {
                "text": "It can be seen from the Fig. 3 that the dependence of the LeNet+Abs accuracy and loss function on the training epoch is not smooth, but much more volatile than those for LeNet-5. There seems to be two reasons for this. First, when training the network, by default, the epoch accuracy is calculated over the last batch, i.e. not over the entire training dataset. The second is that the derivative of the Absolute activation function, indicating the direction of the gradient, is discontinuous at zero argument, so small changes in the argument can lead to sharp changes in the gradient, so the ADAM algorithm does not provide a smooth enough descent, and one should use lower learning rates, slowing down training process. To find the optimally trained model we should find the epoch with maximal accuracy at unknown test dataset. We do not use the test dataset at training, so we may only estimate this accuracy. To prevent overtraining, we should not use train dataset information, and only validation dataset could be used.",
                "cite_spans": [],
                "ref_spans": [
                    {
                        "start": 29,
                        "end": 30,
                        "text": "3",
                        "ref_id": "FIGREF1"
                    }
                ],
                "eq_spans": [],
                "section": "Training process details",
                "sec_num": "3.2"
            },
            {
                "text": "Optimally trained network should provide good accuracy exceeding a given limit at almost any test dataset. After the network trained this minimal accuracy bound should be as high as possible.",
                "cite_spans": [],
                "ref_spans": [],
                "eq_spans": [],
                "section": "Training process details",
                "sec_num": "3.2"
            },
            {
                "text": "To estimate the lower bound of accuracy at any test dataset we should know the distribution of network accuracy at different validation datasets. We have only single validation dataset, so the lower bound could be estimated by bootstrap algorithm [Efron(1979) ]. But for using bootstrap we should accurately choose significance level, that defines how low the lower bound over test dataset should be below the mean validation accuracy. As shows experiments, more accurate results can be obtained when we just choose minimal accuracy over two halves of validation dataset:",
                "cite_spans": [
                    {
                        "start": 247,
                        "end": 259,
                        "text": "[Efron(1979)",
                        "ref_id": "BIBREF15"
                    }
                ],
                "ref_spans": [],
                "eq_spans": [],
                "section": "Training process details",
                "sec_num": "3.2"
            },
            {
                "text": "ACC expected@test = min(ACC(V alidationData1), ACC(V alidationData2))",
                "cite_spans": [],
                "ref_spans": [],
                "eq_spans": [],
                "section": "Training process details",
                "sec_num": "3.2"
            },
            {
                "text": "(6) Another training problem is choosing a right learning rate for training process to be fast and accurate. We reach this by by step-by-step decrease learning rate with reinitializaing ADAM between steps. The ADAM algorithm is known to be very affective, but have hidden parameters, optimized during training. Reinitialization resets these hidden parameters to their initial values. Training process at given learning rate stops if expected accuracy lower bound has not increased for 10 epoches since epoch of previous increase. During training we use learning rates stepping from 10 -3 downto 10 -6 with 10 times decrease between steps. This approach is close to well known ReduceLROnPlateau algorithm with patience 10, monitoring of ACC expected@test and reinitializing ADAM before reduction.",
                "cite_spans": [],
                "ref_spans": [],
                "eq_spans": [],
                "section": "Training process details",
                "sec_num": "3.2"
            },
            {
                "text": "The training algorithm is shown as Algorithm 1",
                "cite_spans": [],
                "ref_spans": [],
                "eq_spans": [],
                "section": "Training process details",
                "sec_num": "3.2"
            },
            {
                "text": "The Table 1 shows the accuracy achieved and total epoch number during training of the standard LeNet-5 model and the LeNet+Abs model (both marked as \"Not degraded\" in the Table 1 ). The table shows that the accuracy of LeNet+Abs exceeds LeNet-5 accuracy, and the number of errors on the test dataset has fallen from 1.14% (for LeNet-5) to 0.56% (for LeNet+Abs)i.e. almost 2 times. Also the found error level 0.56% for LeNet+Abs looks better than the lowest error level 0.7% reported in [Lecun et al.(1998) ] even for boosted variants of LeNet. One can also see that training of LeNet+Abs slower than training LeNet-5 for about 1.5 times (100 training epochs vs. 68 correspondingly).",
                "cite_spans": [
                    {
                        "start": 486,
                        "end": 505,
                        "text": "[Lecun et al.(1998)",
                        "ref_id": "BIBREF9"
                    }
                ],
                "ref_spans": [
                    {
                        "start": 10,
                        "end": 11,
                        "text": "1",
                        "ref_id": "TABREF0"
                    },
                    {
                        "start": 177,
                        "end": 178,
                        "text": "1",
                        "ref_id": "TABREF0"
                    }
                ],
                "eq_spans": [],
                "section": "Training process details",
                "sec_num": "3.2"
            },
            {
                "text": "It is known that an important problem in training deep and recurrent networks is gradient vanishing and explosion -the loss of the network's ability to train",
                "cite_spans": [],
                "ref_spans": [],
                "eq_spans": [],
                "section": "Gradient vanishing robustness",
                "sec_num": "3.3"
            },
            {
                "text": "Algorithm 1 Training procedure procedure CallAfterEachTrainingEpoch(M odel, EpochN umber, V alidationDataset) ExpectedAccuracy \u2190 ACC expected@test (V alidationDataset) if ExpectedAccuracy > BestAccuracy then BestAccuracy \u2190 ExpectedAccuracy BestEpoch \u2190 EpochN umber SaveModel(Model) end if if EpochN umber > BestEpoch + 10 then StopTrainingModel() end if end procedure for LR \u2208 [10 -3 ..10 -6 , step : \u00d70.1] do ADAM \u2190 InitializeADAM (LearningRate = LR)",
                "cite_spans": [],
                "ref_spans": [],
                "eq_spans": [],
                "section": "Gradient vanishing robustness",
                "sec_num": "3.3"
            },
            {
                "text": "if LR < 10 -3 then M odel \u2190 RestoreM odelF romSaved() else M odel \u2190 InitM odel() end if BestEpoch \u2190 0, BestAccuracy \u2190 0 T rainM odelU ntilStop(M odel, ADAM, T rainDataset, V alidationDataset) end for layers with an increase of their number [Bengio et al.(1994) ]. Recently, Residual blocks [He et al.(2015) ] have been found to solve this problem. Let us demonstrate that the Absolute activation function is resistant to the gradient vanishing and explosion effect, not worse than popular ReLU and SeLU functions.",
                "cite_spans": [
                    {
                        "start": 240,
                        "end": 260,
                        "text": "[Bengio et al.(1994)",
                        "ref_id": "BIBREF9"
                    },
                    {
                        "start": 290,
                        "end": 306,
                        "text": "[He et al.(2015)",
                        "ref_id": null
                    }
                ],
                "ref_spans": [],
                "eq_spans": [],
                "section": "Gradient vanishing robustness",
                "sec_num": "3.3"
            },
            {
                "text": "To show this, inside each of the networks (LeNet-5 and LeNet+Abs) 20 intermediate (disturbing) layers were placed (as the last hidden layers), complicating training the network by vanishing gradient. To LeNet-5 and LeNet+Abs architectures a 20 layers with Tanh, ReLU, SeSU, Abs activations were added, producing 8 final architures: Lenet-5+20DTanh, Lenet-5+20DReLU, Lenet-5+20DSeLU, Lenet-5+20DAbs, Lenet+Abs+20DTanh, Lenet+Abs+20DReLU, Lenet+Abs+20DSeLU, Lenet+Abs+20DAbs. Examples of these architectures are shown in Fig. 4 .",
                "cite_spans": [],
                "ref_spans": [
                    {
                        "start": 524,
                        "end": 525,
                        "text": "4",
                        "ref_id": "FIGREF2"
                    }
                ],
                "eq_spans": [],
                "section": "Gradient vanishing robustness",
                "sec_num": "3.3"
            },
            {
                "text": "All 8 resulting (deep) networks have 511226 free coefficients, and about 143 thousand of them are from the last (disturbing) layers, and these networks differ only by activation functions in layers.",
                "cite_spans": [],
                "ref_spans": [],
                "eq_spans": [],
                "section": "Gradient vanishing robustness",
                "sec_num": "3.3"
            },
            {
                "text": "The training results are shown in Table 1 .",
                "cite_spans": [],
                "ref_spans": [
                    {
                        "start": 40,
                        "end": 41,
                        "text": "1",
                        "ref_id": "TABREF0"
                    }
                ],
                "eq_spans": [],
                "section": "Gradient vanishing robustness",
                "sec_num": "3.3"
            },
            {
                "text": "It can be seen from the Table 1 that adding 20 more hidden layers with Abs activation at the end makes it still possible to train LeNet+Abs+20DAbs, although with somewhat lower accuracy than in the absence of these layers -LeNet+Abs network (99.05% vs. 99.44% correspondingly). This confirms with our theoretical expectation that the Absolute activation function does not cause significant gradient vanishing or explosion, and therefore can be effectively used ",
                "cite_spans": [],
                "ref_spans": [
                    {
                        "start": 30,
                        "end": 31,
                        "text": "1",
                        "ref_id": "TABREF0"
                    }
                ],
                "eq_spans": [],
                "section": "Gradient vanishing robustness",
                "sec_num": "3.3"
            },
            {
                "text": "The good stability of the Absolute activation function against gradient vanishing suggests that the original LeNet-5 neural network could be too complex for its reported accuracy. Let us reduce its size without loosing the accuracy. The most obvious way is to remove the last hidden convolutional layer from LeNet+Abs. This resulting network referred as SmallLeNet+Abs network and shown in Fig. 5A . The TinyLeNet+Abs model is made from the Small-LeNet+Abs model by reducing the number of convolutions in the second convolution layer from 16 to 3. This new architecture is also shown in Fig. 5B . Bold marks important changes.",
                "cite_spans": [],
                "ref_spans": [
                    {
                        "start": 395,
                        "end": 397,
                        "text": "5A",
                        "ref_id": null
                    },
                    {
                        "start": 592,
                        "end": 594,
                        "text": "5B",
                        "ref_id": null
                    }
                ],
                "eq_spans": [],
                "section": "Reducing the LeNet-5 network size without loss of accuracy",
                "sec_num": "3.4"
            },
            {
                "text": "The Table 2 shows the accuracies achieved by these networks using training Algorithm 1. In addition, the number of trained model coefficients, total trained epoches, and bootstrap confidence interval on the test dataset are shown (with a standard significance level of 0.95).",
                "cite_spans": [],
                "ref_spans": [
                    {
                        "start": 10,
                        "end": 11,
                        "text": "2",
                        "ref_id": "TABREF1"
                    }
                ],
                "eq_spans": [],
                "section": "Reducing the LeNet-5 network size without loss of accuracy",
                "sec_num": "3.4"
            },
            {
                "text": "The Table 2 shows that the best accuracy on the test dataset is provided by the LeNet+Abs model. The SmallLeNet+Abs model with 52 thousand trained parameters, and TinyLeNet+Abs model with 10.6 thousand trained parameters also exceeds the initial LeNet-5 (with 368 thousand parameters) accuracy in Bold highlights the main difference from the previous model. 5C ), provides the even better accuracy than LeNet+Abs architecture -99.51%, but having 4.8 times less parameters.",
                "cite_spans": [],
                "ref_spans": [
                    {
                        "start": 10,
                        "end": 11,
                        "text": "2",
                        "ref_id": "TABREF1"
                    },
                    {
                        "start": 358,
                        "end": 360,
                        "text": "5C",
                        "ref_id": null
                    }
                ],
                "eq_spans": [],
                "section": "Reducing the LeNet-5 network size without loss of accuracy",
                "sec_num": "3.4"
            },
            {
                "text": "Thus, the replacement of Tanh activation functions with Abs makes it possible to reduce the size of original LeNet-5 model by more than 4.8 and 7 times with an improvement of its accuracy (LeNet+Conv120+Abs and Small-LeNet+Abs variants correspondingly), and providing better accuracy than ReLU and SeLU variants. It can be seen from the bootstrap confidence intervals that even TinyLeNet+Abs model with the number of parameters 35 times less than the number of LeNet-5 parameters provides an accuracy that not worse than the accuracy of original LeNet-5 with Tanh, ReLU, or SeLU activations.",
                "cite_spans": [],
                "ref_spans": [],
                "eq_spans": [],
                "section": "Reducing the LeNet-5 network size without loss of accuracy",
                "sec_num": "3.4"
            },
            {
                "text": "As we have shown, even standard LeNet-5 with Abs activation (LeNet+Abs) can provide very good accuracy (99.44%) comparable with top solutions for fixed shape activation functions [Apicella et al.(2021) ]. Extended LeNet versions (Lenet+Conv120+Abs) have accuracy up to (99.51%), very close to top solutions for fixed shape activation functions [Apicella et al.(2021) ], and having less than 77,000 trained parameters.",
                "cite_spans": [
                    {
                        "start": 179,
                        "end": 201,
                        "text": "[Apicella et al.(2021)",
                        "ref_id": "BIBREF13"
                    },
                    {
                        "start": 344,
                        "end": 366,
                        "text": "[Apicella et al.(2021)",
                        "ref_id": "BIBREF13"
                    }
                ],
                "ref_spans": [],
                "eq_spans": [],
                "section": "Reducing the LeNet-5 network size without loss of accuracy",
                "sec_num": "3.4"
            },
            {
                "text": "As we have shown above, the networks with Abs activation looks better than the networks with ReLU, SeLU and Tanh activations. But there are two problems arise. Problem 1. The stabuility of training the network. We use random initial network parameters, no regularization, so the found loss function minimum is not global one. We need to check how the initializing and training affect the trained network accuracy.",
                "cite_spans": [],
                "ref_spans": [],
                "eq_spans": [],
                "section": "More efficient accuracy predictions for training",
                "sec_num": "4"
            },
            {
                "text": "Problem 2. The stop condition. As a stop condition we use prediction of network accuracy at unknown test dataset over validation dataset. It is obvious that different prediction algorithms lead to different network accuracy.",
                "cite_spans": [],
                "ref_spans": [],
                "eq_spans": [],
                "section": "More efficient accuracy predictions for training",
                "sec_num": "4"
            },
            {
                "text": "To study these problems we created 3 ensembles for LeNet+Conv120 network architecture (LeNet+Conv120+Abs, LeNet+Conv120+ReLU, LeNet+Conv120+SeLU, LeNet+Conv120+Tanh), that differs only by activation function (Abs, ReLU, SeLU, Tanh). Each of 3 ensembles is trained by using different model for accuracy at test dataset prediction over validation dataset ( ACC expected@test in Algorithm 1 ):",
                "cite_spans": [],
                "ref_spans": [],
                "eq_spans": [],
                "section": "More efficient accuracy predictions for training",
                "sec_num": "4"
            },
            {
                "text": "EQUATION",
                "cite_spans": [],
                "ref_spans": [],
                "eq_spans": [
                    {
                        "start": 0,
                        "end": 8,
                        "text": "EQUATION",
                        "ref_id": "EQREF",
                        "raw_str": "ACC expected@test,1 = min(ACC(V alidationData1), ACC(V alidationData2))",
                        "eq_num": "(7)"
                    }
                ],
                "section": "More efficient accuracy predictions for training",
                "sec_num": "4"
            },
            {
                "text": "EQUATION",
                "cite_spans": [],
                "ref_spans": [],
                "eq_spans": [
                    {
                        "start": 0,
                        "end": 8,
                        "text": "EQUATION",
                        "ref_id": "EQREF",
                        "raw_str": "ACC expected@test,2 = M EAN bootstrap (V alidationData)-ST D bootstrap (V alidationData)",
                        "eq_num": "(8)"
                    }
                ],
                "section": "More efficient accuracy predictions for training",
                "sec_num": "4"
            },
            {
                "text": "EQUATION",
                "cite_spans": [],
                "ref_spans": [],
                "eq_spans": [
                    {
                        "start": 0,
                        "end": 8,
                        "text": "EQUATION",
                        "ref_id": "EQREF",
                        "raw_str": "ACC expected@test,3 = ACC expected@test,1 -ST D bootstrap (V alidationData) (",
                        "eq_num": "9"
                    }
                ],
                "section": "More efficient accuracy predictions for training",
                "sec_num": "4"
            },
            {
                "text": ")",
                "cite_spans": [],
                "ref_spans": [],
                "eq_spans": [],
                "section": "More efficient accuracy predictions for training",
                "sec_num": "4"
            },
            {
                "text": "The first prediction method is discussed earlier with Algorithm 1, the second one is based on bootstrap estimate of lower bound of prediction interval over validation dataset with significance level 0.68, the last one is combination of the first and the second, lowering the expected bound.",
                "cite_spans": [],
                "ref_spans": [],
                "eq_spans": [],
                "section": "More efficient accuracy predictions for training",
                "sec_num": "4"
            },
            {
                "text": "Each ensemble of trained networks were used to produce 2 values, shown in Table 3 . The first one is the accuracy over the test dataset by majority ensemble voting, when the predicted label is found as the label predicted by maximal number of networks (marked as M.V. -majority voting). Another measure is prediction interval over the test dataset over the ensemble of trained networks (marked as C.I. -confidence interval).",
                "cite_spans": [],
                "ref_spans": [
                    {
                        "start": 80,
                        "end": 81,
                        "text": "3",
                        "ref_id": null
                    }
                ],
                "eq_spans": [],
                "section": "More efficient accuracy predictions for training",
                "sec_num": "4"
            },
            {
                "text": "For different purposes different M.V. and C.I. are required. For example, for majority ensemble voting the networks should be overtrained and M.V. should be as high as possible. As shown in Table 3 , for Abs network the best M.V. is provided by use ACC expected@test,1 or ACC expected@test,3 accuracy prediction variant during train.",
                "cite_spans": [],
                "ref_spans": [
                    {
                        "start": 196,
                        "end": 197,
                        "text": "3",
                        "ref_id": null
                    }
                ],
                "eq_spans": [],
                "section": "More efficient accuracy predictions for training",
                "sec_num": "4"
            },
            {
                "text": "When only single network is planned for prediction, we need the highest confidential interval. In this case using ACC expected@test,3 prediction variant is preferable. For both cases using ACC expected@test,3 accuracy prediction for training the LeNet+Conv120+Abs is preferable.",
                "cite_spans": [],
                "ref_spans": [],
                "eq_spans": [],
                "section": "More efficient accuracy predictions for training",
                "sec_num": "4"
            },
            {
                "text": "To improve the result, a LeNet+Conv64+Conv120+Abs were made -it is wider and deeper LeNet-like network, having more convolutions at top layer, than LeNet+Conv120+Abs has. Its architecture is shown in Fig. 5D .",
                "cite_spans": [],
                "ref_spans": [
                    {
                        "start": 205,
                        "end": 207,
                        "text": "5D",
                        "ref_id": null
                    }
                ],
                "eq_spans": [],
                "section": "More efficient accuracy predictions for training",
                "sec_num": "4"
            },
            {
                "text": "The model has 227474 parameters, that is also smaller than number of parameters in original LeNet-5 network, and provides better accuracy than LeNet+Conv120+Abs. It's ensemble training using ACC expected@test,3 test dataset accuracy prediction shows its increased accuracy, also exceding its ReLU, SeLU and Tanh varaints (shown in Table 3 ).",
                "cite_spans": [],
                "ref_spans": [
                    {
                        "start": 337,
                        "end": 338,
                        "text": "3",
                        "ref_id": null
                    }
                ],
                "eq_spans": [],
                "section": "More efficient accuracy predictions for training",
                "sec_num": "4"
            },
            {
                "text": "In the paper we discuss the Absolute activation function for classification neural networks. An examples of using this activation function in simple and complex classifying problems are presented. In solving the MNIST problem with the LeNet-5 network, the efficiency of Abs is shown in comparison with Tanh, ReLU and SeLU activations. It allows to reach 99.44% accuracy at standard LeNet-5 network by only changing all activations into Abs. It is shown that its use practically does not lead to gradient vanishing/explosion, and therefore Absolute activation can be used in both small and deep neural networks. It is shown that in solving the MNIST problem with the LeNet-5 architecture, the use of Absolute activation helps to significantly reduce the size of the neural network (up to 2 orders by number of trained parameters) and improve the accuracy of the solution. The mean reached accuracy could be about 99.51% ([99.41%..99.59%] at different trained varaints) at train dataset with decreasing the network size from 368 thousands to 76 thousands coeficients(LeNet+Conv120+Abs) and about 99.53% ([99.45%..99.60%] at different trained varaints) at train dataset with decreasing the network size from 368 thousands to 227 thousands coeficients(LeNet+Conv64+Conv120+Abs). Therefore these networks with Absolute activations could be close to the best solutions accuracy for fixed shape activation functions, reached by more complicated networks [Apicella et al.(2021) ].",
                "cite_spans": [
                    {
                        "start": 1447,
                        "end": 1469,
                        "text": "[Apicella et al.(2021)",
                        "ref_id": "BIBREF13"
                    }
                ],
                "ref_spans": [],
                "eq_spans": [],
                "section": "Conclusion",
                "sec_num": "5"
            },
            {
                "text": "It is demonstrated that training curve (accuracy vs. training epoch) when using Abs activation is not smooth, so one should use more complex technique for changing learning ratio and stop training. We doing this by estimating the lower bound of network accuracy at any test dataset using accuracy calculated Table 3 : Accuracy results for ensemble of from 20 training runs, produced 20 trained variants of LeNet+Conv120 and LeNet+Conv64+Conv120 networks, with different algorithms for predicting accuracy at test dataset from the validation dataset during training, eqs.7-9. M.V. rows -majority voting ensemble accuracy over 20 networks at test dataset, C.I. rows -accuracy limits over the ensemble at test dataset. Best results marked by bold.",
                "cite_spans": [],
                "ref_spans": [
                    {
                        "start": 314,
                        "end": 315,
                        "text": "3",
                        "ref_id": null
                    }
                ],
                "eq_spans": [],
                "section": "Conclusion",
                "sec_num": "5"
            },
            {
                "text": "ACC expected@test,1 ACC expected@test,2 ACC expected@test,3 Lenet+Conv120 architecture +Tanh C.I.",
                "cite_spans": [],
                "ref_spans": [],
                "eq_spans": [],
                "section": "Conclusion",
                "sec_num": "5"
            },
            {
                "text": "[98.95,99.20] [98.93,99.21] [99.03,99.22] +Tanh M.V. 99.33 99.32 99.36 +ReLU C.I.",
                "cite_spans": [],
                "ref_spans": [],
                "eq_spans": [],
                "section": "Conclusion",
                "sec_num": "5"
            },
            {
                "text": "[99.12,99.38] [99.16,99.37] [99.13,99.37] +ReLU M.V. 99.52 99.52 99.48 +SeLU C.I.",
                "cite_spans": [],
                "ref_spans": [],
                "eq_spans": [],
                "section": "Conclusion",
                "sec_num": "5"
            },
            {
                "text": "[99.19,99.36] [99.17,99.39] [99.20,99.35] +SeLU M.V. 99.54 99.55 99.54 +Abs C.I.",
                "cite_spans": [],
                "ref_spans": [],
                "eq_spans": [],
                "section": "Conclusion",
                "sec_num": "5"
            },
            {
                "text": "[99.39,99.56] [99.35,99.57] [99.41,99.59] +Abs M.V.",
                "cite_spans": [],
                "ref_spans": [],
                "eq_spans": [],
                "section": "Conclusion",
                "sec_num": "5"
            },
            {
                "text": "99.64 99.61 99.64 Lenet+Conv64+Conv120 architecture +Tanh C.I.",
                "cite_spans": [],
                "ref_spans": [],
                "eq_spans": [],
                "section": "Conclusion",
                "sec_num": "5"
            },
            {
                "text": "[98.87,99.15] +Tanh M.V. 99.37 +ReLU C.I.",
                "cite_spans": [],
                "ref_spans": [],
                "eq_spans": [],
                "section": "Conclusion",
                "sec_num": "5"
            },
            {
                "text": "[99.24,99.50] +ReLU M.V. 99.55 +SeLU C.I.",
                "cite_spans": [],
                "ref_spans": [],
                "eq_spans": [],
                "section": "Conclusion",
                "sec_num": "5"
            },
            {
                "text": "[99.29,99.44] +SeLU M.V. 99.56 +Abs C.I.",
                "cite_spans": [],
                "ref_spans": [],
                "eq_spans": [],
                "section": "Conclusion",
                "sec_num": "5"
            },
            {
                "text": "[99.45,99.60] +Abs M.V.",
                "cite_spans": [],
                "ref_spans": [],
                "eq_spans": [],
                "section": "Conclusion",
                "sec_num": "5"
            },
            {
                "text": "over the halves of validating dataset and by bootstrap method and combining these predictions. Thus, the high efficiency of the Absolute activation function has been demonstrated, which makes it possible to improve the accuracy of current classification neural networks even without changing their architecture.",
                "cite_spans": [],
                "ref_spans": [],
                "eq_spans": [],
                "section": "99.64",
                "sec_num": null
            }
        ],
        "back_matter": [
            {
                "text": "The data analysis was performed in part on the equipment of the Bioinformatics Shared Access Center, the Federal Research Center Institute of Cytology and Genetics of Siberian Branch of the Russian Academy of Sciences (ICG SB RAS). The work has been done under financial support of the Ministry of Science and Higher Education of the Russian Federation (Subsidy No.075-GZ/C3569/278).",
                "cite_spans": [],
                "ref_spans": [],
                "eq_spans": [],
                "section": "Acknowledgements",
                "sec_num": null
            }
        ],
        "bib_entries": {
            "BIBREF0": {
                "ref_id": "b0",
                "title": "Distilling the knowledge in a neural network",
                "authors": [
                    {
                        "first": "",
                        "middle": [],
                        "last": "Hinton",
                        "suffix": ""
                    }
                ],
                "year": 2015,
                "venue": "",
                "volume": "",
                "issue": "",
                "pages": "",
                "other_ids": {},
                "num": null,
                "urls": [],
                "raw_text": "Hinton et al.(2015)] Geoffrey Hinton, Oriol Vinyals, and Jeff Dean. Distilling the knowledge in a neural network, 2015.",
                "links": null
            },
            "BIBREF1": {
                "ref_id": "b1",
                "title": "On the representation of continuous functions of many variables by superposition of continuous functions of one variable and addition",
                "authors": [
                    {
                        "first": "A",
                        "middle": [
                            "N"
                        ],
                        "last": "Kolmogorov",
                        "suffix": ""
                    }
                ],
                "year": 1957,
                "venue": "Dokl. Akad. Nauk SSSR",
                "volume": "",
                "issue": "",
                "pages": "953--956",
                "other_ids": {},
                "num": null,
                "urls": [],
                "raw_text": "A.N. Kolmogorov. On the representation of continuous functions of many variables by superposition of continuous functions of one variable and addition. Dokl. Akad. Nauk SSSR, pages 953-956, 1957.",
                "links": null
            },
            "BIBREF2": {
                "ref_id": "b2",
                "title": "On the function of three variables",
                "authors": [
                    {
                        "first": "Arnold",
                        "middle": [
                            ";"
                        ],
                        "last": "",
                        "suffix": ""
                    },
                    {
                        "first": "Vladimir",
                        "middle": [],
                        "last": "Arnold",
                        "suffix": ""
                    }
                ],
                "year": 1963,
                "venue": "Amer. Math. Soc. Transl",
                "volume": "",
                "issue": "",
                "pages": "51--54",
                "other_ids": {},
                "num": null,
                "urls": [],
                "raw_text": "Arnold(1963)] Vladimir Arnold. On the function of three variables. Amer. Math. Soc. Transl., pages 51-54, 1963.",
                "links": null
            },
            "BIBREF3": {
                "ref_id": "b3",
                "title": "Approximation by superpositions of a sigmoidal function",
                "authors": [
                    {
                        "first": ";",
                        "middle": [
                            "G"
                        ],
                        "last": "Cybenko",
                        "suffix": ""
                    },
                    {
                        "first": "",
                        "middle": [],
                        "last": "Cybenko",
                        "suffix": ""
                    }
                ],
                "year": 1989,
                "venue": "Mathematics of Control, Signals, and Systems",
                "volume": "2",
                "issue": "4",
                "pages": "303--314",
                "other_ids": {
                    "DOI": [
                        "10.1007/bf02551274"
                    ]
                },
                "num": null,
                "urls": [],
                "raw_text": "Cybenko(1989)] G. Cybenko. Approximation by superpositions of a sigmoidal function. Mathematics of Control, Signals, and Systems, 2(4):303-314, 1989. doi: 10.1007/bf02551274.",
                "links": null
            },
            "BIBREF4": {
                "ref_id": "b4",
                "title": "On the approximate realization of continuous mappings by neural networks",
                "authors": [
                    {
                        "first": "Ken-Ichi",
                        "middle": [],
                        "last": "Funahashi",
                        "suffix": ""
                    },
                    {
                        "first": "",
                        "middle": [],
                        "last": "Funahashi",
                        "suffix": ""
                    }
                ],
                "year": 1989,
                "venue": "Neural Networks",
                "volume": "2",
                "issue": "3",
                "pages": "183--192",
                "other_ids": {
                    "DOI": [
                        "10.1016/0893-6080(89)90003-8"
                    ]
                },
                "num": null,
                "urls": [],
                "raw_text": "Funahashi(1989)] Ken-Ichi Funahashi. On the approximate realization of con- tinuous mappings by neural networks. Neural Networks, 2(3):183-192, 1989. doi: 10.1016/0893-6080(89)90003-8.",
                "links": null
            },
            "BIBREF5": {
                "ref_id": "b5",
                "title": "Multilayer feedforward networks are universal approximators",
                "authors": [
                    {
                        "first": "",
                        "middle": [],
                        "last": "Hornik",
                        "suffix": ""
                    }
                ],
                "year": 1989,
                "venue": "Neural Networks",
                "volume": "2",
                "issue": "5",
                "pages": "359--366",
                "other_ids": {
                    "DOI": [
                        "10.1016/0893-6080(89)90020-8"
                    ]
                },
                "num": null,
                "urls": [],
                "raw_text": "Hornik et al.(1989)] Kurt Hornik, Maxwell Stinchcombe, and Halbert White. Multilayer feedforward networks are universal approximators. Neural Net- works, 2(5):359-366, 1989. doi: 10.1016/0893-6080(89)90020-8.",
                "links": null
            },
            "BIBREF6": {
                "ref_id": "b6",
                "title": "Approximation capabilities of multilayer feedforward networks",
                "authors": [
                    {
                        "first": "Kurt",
                        "middle": [],
                        "last": "Hornik",
                        "suffix": ""
                    },
                    {
                        "first": "",
                        "middle": [],
                        "last": "Hornik",
                        "suffix": ""
                    }
                ],
                "year": 1991,
                "venue": "Neural Networks",
                "volume": "4",
                "issue": "2",
                "pages": "",
                "other_ids": {
                    "DOI": [
                        "10.1016/0893-6080"
                    ]
                },
                "num": null,
                "urls": [],
                "raw_text": "Hornik(1991)] Kurt Hornik. Approximation capabilities of multilayer feed- forward networks. Neural Networks, 4(2):251-257, 1991. doi: 10.1016/ 0893-6080(91)90009-T.",
                "links": null
            },
            "BIBREF7": {
                "ref_id": "b7",
                "title": "Neural network with unbounded activation functions is universal approximator",
                "authors": [
                    {
                        "first": "Murata",
                        "middle": [],
                        "last": "Sonoda",
                        "suffix": ""
                    },
                    {
                        "first": "Sho",
                        "middle": [],
                        "last": "Sonoda",
                        "suffix": ""
                    },
                    {
                        "first": "Noboru",
                        "middle": [],
                        "last": "Murata",
                        "suffix": ""
                    }
                ],
                "year": 2017,
                "venue": "Applied and Computational Harmonic Analysis",
                "volume": "43",
                "issue": "2",
                "pages": "233--268",
                "other_ids": {
                    "DOI": [
                        "10.1016/j.acha.2015.12.005"
                    ]
                },
                "num": null,
                "urls": [],
                "raw_text": "Sonoda and Murata(2017)] Sho Sonoda and Noboru Murata. Neural network with unbounded activation functions is universal approximator. Applied and Computational Harmonic Analysis, 43(2):233-268, 2017. doi: 10.1016/ j.acha.2015.12.005.",
                "links": null
            },
            "BIBREF8": {
                "ref_id": "b8",
                "title": "Abien Fred Agarap. Deep Learning using Rectified Linear Units (ReLU)",
                "authors": [
                    {
                        "first": "",
                        "middle": [],
                        "last": "Agarap",
                        "suffix": ""
                    }
                ],
                "year": 2018,
                "venue": "",
                "volume": "",
                "issue": "",
                "pages": "",
                "other_ids": {},
                "num": null,
                "urls": [],
                "raw_text": "Agarap(2018)] Abien Fred Agarap. Deep Learning using Rectified Linear Units (ReLU), 2018.",
                "links": null
            },
            "BIBREF9": {
                "ref_id": "b9",
                "title": "Learning longterm dependencies with gradient descent is difficult",
                "authors": [
                    {
                        "first": "",
                        "middle": [],
                        "last": "Bengio",
                        "suffix": ""
                    }
                ],
                "year": 1994,
                "venue": "IEEE Transactions on Neural Networks",
                "volume": "5",
                "issue": "2",
                "pages": "2278--2324",
                "other_ids": {
                    "DOI": [
                        "10.1109/72.279181"
                    ]
                },
                "num": null,
                "urls": [],
                "raw_text": "Bengio et al.(1994)] Y. Bengio, P. Simard, and P. Frasconi. Learning long- term dependencies with gradient descent is difficult. IEEE Transactions on Neural Networks, 5(2):157-166, 1994. doi: 10.1109/72.279181. [Lecun et al.(1998)] Y. Lecun, L. Bottou, Y. Bengio, and P. Haffner. Gradient- based learning applied to document recognition. Proceedings of the IEEE, 86(11):2278-2324, 1998. doi: 10.1109/5.726791.",
                "links": null
            },
            "BIBREF10": {
                "ref_id": "b10",
                "title": "Kaiming He, Xiangyu Zhang, Shaoqing Ren, and Jian Sun. Deep residual learning for image recognition",
                "authors": [
                    {
                        "first": "",
                        "middle": [],
                        "last": "Krizhevsky",
                        "suffix": ""
                    }
                ],
                "year": 2015,
                "venue": "Communications of the ACM",
                "volume": "60",
                "issue": "",
                "pages": "84--90",
                "other_ids": {
                    "DOI": [
                        "10.1145/3065386"
                    ]
                },
                "num": null,
                "urls": [],
                "raw_text": "Krizhevsky et al.(2017)] Alex Krizhevsky, Ilya Sutskever, and Geoffrey E. Hin- ton. ImageNet classification with deep convolutional neural networks. Com- munications of the ACM, 60(6):84-90, 2017. doi: 10.1145/3065386. [He et al.(2015)] Kaiming He, Xiangyu Zhang, Shaoqing Ren, and Jian Sun. Deep residual learning for image recognition, 2015.",
                "links": null
            },
            "BIBREF11": {
                "ref_id": "b11",
                "title": "APTx: better activation function than MISH, SWISH, and ReLU's variants used in deep learning",
                "authors": [
                    {
                        "first": "Ravin",
                        "middle": [],
                        "last": "Kumar",
                        "suffix": ""
                    }
                ],
                "year": 2022,
                "venue": "",
                "volume": "",
                "issue": "",
                "pages": "",
                "other_ids": {
                    "DOI": [
                        "10.48550/ARXIV.2209.06119"
                    ]
                },
                "num": null,
                "urls": [],
                "raw_text": "Ravin Kumar. APTx: better activation function than MISH, SWISH, and ReLU's variants used in deep learning. 2022. doi: 10.48550/ ARXIV.2209.06119.",
                "links": null
            },
            "BIBREF12": {
                "ref_id": "b12",
                "title": "AANN: Absolute Artificial Neural Network",
                "authors": [
                    {
                        "first": "Animesh",
                        "middle": [],
                        "last": "Karnewar",
                        "suffix": ""
                    },
                    {
                        "first": "",
                        "middle": [],
                        "last": "Karnewar",
                        "suffix": ""
                    }
                ],
                "year": 2018,
                "venue": "2018 3rd International Conference for Convergence in Technology",
                "volume": "",
                "issue": "",
                "pages": "",
                "other_ids": {
                    "DOI": [
                        "10.1109/i2ct.2018.8529552"
                    ]
                },
                "num": null,
                "urls": [],
                "raw_text": "Karnewar(2018)] Animesh Karnewar. AANN: Absolute Artificial Neural Net- work. In 2018 3rd International Conference for Convergence in Technology (I2CT), 2018. doi: 10.1109/i2ct.2018.8529552.",
                "links": null
            },
            "BIBREF13": {
                "ref_id": "b13",
                "title": "A survey on modern trainable activation functions",
                "authors": [
                    {
                        "first": "",
                        "middle": [],
                        "last": "Apicella",
                        "suffix": ""
                    }
                ],
                "year": 2014,
                "venue": "Neural Networks",
                "volume": "138",
                "issue": "",
                "pages": "14--32",
                "other_ids": {
                    "DOI": [
                        "10.1016/j.neunet.2021.01.026"
                    ]
                },
                "num": null,
                "urls": [],
                "raw_text": "Apicella et al.(2021)] Andrea Apicella, Francesco Donnarumma, Francesco Isgr\u00f2, and Roberto Prevete. A survey on modern trainable activation func- tions. Neural Networks, 138:14-32, 2021. doi: 10.1016/j.neunet.2021.01. 026. [Kingma and Ba(2014)] Diederik P. Kingma and Jimmy Ba. Adam: A Method for Stochastic Optimization, 2014.",
                "links": null
            },
            "BIBREF14": {
                "ref_id": "b14",
                "title": "Best practices for convolutional neural networks applied to visual document analysis",
                "authors": [
                    {
                        "first": "",
                        "middle": [],
                        "last": "Simard",
                        "suffix": ""
                    }
                ],
                "year": 2003,
                "venue": "Seventh International Conference on Document Analysis and Recognition",
                "volume": "",
                "issue": "",
                "pages": "",
                "other_ids": {
                    "DOI": [
                        "10.1109/icdar.2003.1227801"
                    ]
                },
                "num": null,
                "urls": [],
                "raw_text": "Simard et al.(2003)] P.Y. Simard, D. Steinkraus, and J.C. Platt. Best prac- tices for convolutional neural networks applied to visual document analysis. In Seventh International Conference on Document Analysis and Recogni- tion, 2003. Proceedings. IEEE Comput. Soc, 2003. doi: 10.1109/icdar.2003. 1227801.",
                "links": null
            },
            "BIBREF15": {
                "ref_id": "b15",
                "title": "Bootstrap Methods: Another Look at the Jackknife",
                "authors": [
                    {
                        "first": ";",
                        "middle": [
                            "B"
                        ],
                        "last": "Efron",
                        "suffix": ""
                    },
                    {
                        "first": "",
                        "middle": [],
                        "last": "Efron",
                        "suffix": ""
                    }
                ],
                "year": 1979,
                "venue": "The Annals of Statistics",
                "volume": "7",
                "issue": "1",
                "pages": "1--26",
                "other_ids": {
                    "DOI": [
                        "10.1214/aos/1176344552"
                    ]
                },
                "num": null,
                "urls": [],
                "raw_text": "Efron(1979)] B. Efron. Bootstrap Methods: Another Look at the Jackknife. The Annals of Statistics, 7(1):1 -26, 1979. doi: 10.1214/aos/1176344552.",
                "links": null
            }
        },
        "ref_entries": {
            "FIGREF0": {
                "uris": null,
                "text": "Figure 1: Synthetic datasets for the simplest classification: A) linear separation; B) \"cross\" separation; C) circular area",
                "num": null,
                "fig_num": "1",
                "type_str": "figure"
            },
            "FIGREF1": {
                "uris": null,
                "text": "Figure3: Tested network architectures: A) standard LeNet-5; B) LeNet+Abs (with Absolute activation functions). The results of training the two networks, from top to bottom: loss on the test and validation datasets, accuracy (accuracy) on the training and validation datasets.",
                "num": null,
                "fig_num": "3",
                "type_str": "figure"
            },
            "FIGREF2": {
                "uris": null,
                "text": "Figure 4: Degraded versions of LeNet-5 and LeNet+Abs networks to test the effect of gradient vanisning and explosion effect: LeNet-5+20DTanh (A), LeNet+Abs+20DAbs (B) , LeNet-5+20Drelu (C), LeNet+Abs+20Drelu (D). Architecture and quality of training.",
                "num": null,
                "fig_num": "4",
                "type_str": "figure"
            },
            "FIGREF3": {
                "uris": null,
                "text": "Figure 5: Smaller models A)SmallLeNet+Abs; B)TinyLeNet+Abs; C)LeNet+Conv120+Abs; D)LeNet+Conv64+Conv120+Abs.Bold highlights the main difference from the previous model.",
                "num": null,
                "fig_num": "1",
                "type_str": "figure"
            },
            "TABREF0": {
                "text": "Accuracy (%) of various networks -standard LeNet-5 and LeNet+Abs, degraded by the last 20 hidden fully connected layers with different activation functions. *) marks the cases when learning rate 10 -3 is not enought to start training and we start from 10 -4 instead. Bootstrap confidential interval over test dataset at standard confidence level 0.95 is also shown.",
                "num": null,
                "type_str": "table",
                "html": null,
                "content": "<table><tr><td>Network</td><td colspan=\"3\">Accuracy Trained Epoches Conf.interval</td></tr><tr><td colspan=\"2\">LeNet-5 architecture</td><td/><td/></tr><tr><td>Not degraded</td><td>98.86</td><td>68</td><td>(98.65, 99.07)</td></tr><tr><td>+20DTanh</td><td>98.41</td><td>80</td><td>(98.17,98.66)</td></tr><tr><td>+20DReLU</td><td>98.32</td><td>129</td><td>(98.07,98.57)</td></tr><tr><td>+20DSeLU</td><td>98.75</td><td>80</td><td>(98.53,98.97)</td></tr><tr><td>+20DAbs(*)</td><td>98.71</td><td>66</td><td>(98.49,98.93)</td></tr><tr><td colspan=\"2\">LeNet+Abs architecture</td><td/><td/></tr><tr><td>Not degraded</td><td>99.44</td><td>100</td><td>(99.30,99.59)</td></tr><tr><td>+20DTanh(*)</td><td>97.51</td><td>80</td><td>(96.90,97.54)</td></tr><tr><td>+20DReLU</td><td>98.92</td><td>118</td><td>(98.72,99.12)</td></tr><tr><td>+20DSeLU</td><td>99.03</td><td>98</td><td>(98.84,99.22)</td></tr><tr><td>+20DAbs</td><td>99.05</td><td>112</td><td>(98.86,99.24)</td></tr></table>"
            },
            "TABREF1": {
                "text": "The best accuracy obtained on test dataset for different architectures with different activation functions. The number of trained model parameters and the bootstrap confidence interval (standard confidence level 0.95) over the test dataset. Bold marks best activation function for given architecture. ACC expected@test according to eq.6.",
                "num": null,
                "type_str": "table",
                "html": null,
                "content": "<table><tr><td/><td colspan=\"3\">Accuracy Trained epoches Conf.interval</td><td># coefs</td></tr><tr><td colspan=\"2\">LeNet architecture</td><td/><td/><td>368426</td></tr><tr><td>+Tanh</td><td>98.86</td><td>68</td><td>(98.65, 99.07)</td><td>368426</td></tr><tr><td>(LeNet-5)</td><td/><td/><td/><td/></tr><tr><td>+ ReLU</td><td>99.13</td><td>72</td><td>(98.95,99.31)</td><td>-</td></tr><tr><td>+ SeLU</td><td>99.03</td><td>62</td><td>(98.84,99.23)</td><td>-</td></tr><tr><td>+ Abs</td><td>99.44</td><td>100</td><td>(99.30,99.58)</td><td>-</td></tr><tr><td colspan=\"2\">SmallLeNet architecture</td><td/><td/><td>51890</td></tr><tr><td>+ Tanh</td><td>99.03</td><td>64</td><td>(98.84, 99.22)</td><td>51890</td></tr><tr><td>+ Relu</td><td>99.10</td><td>88</td><td>(98.91, 99.28)</td><td>-</td></tr><tr><td>+ Selu</td><td>99.10</td><td>59</td><td>(98.92, 99.28)</td><td>-</td></tr><tr><td>+ Abs</td><td>99.28</td><td>116</td><td>(99.12, 99.44)</td><td>-</td></tr><tr><td colspan=\"2\">TinyLeNet architecture</td><td/><td/><td>10615</td></tr><tr><td>+ Tanh</td><td>98.76</td><td>75</td><td>(98.54, 98.97)</td><td>10615</td></tr><tr><td>+ Relu</td><td>98.94</td><td>71</td><td>(98.74, 99.14)</td><td>-</td></tr><tr><td>+ Selu</td><td>98.65</td><td>74</td><td>(98.42, 98.88)</td><td>-</td></tr><tr><td>+ Abs</td><td>99.08</td><td>87</td><td>(98.90, 99.27)</td><td>-</td></tr><tr><td colspan=\"2\">LeNet+Conv120 architecture</td><td/><td/><td>76226</td></tr><tr><td>+ Tanh</td><td>99.09</td><td>72</td><td>(98.91, 99.27)</td><td>-</td></tr><tr><td>+ Relu</td><td>99.28</td><td>80</td><td>(99.12, 99.45)</td><td>-</td></tr><tr><td>+ Selu</td><td>99.26</td><td>65</td><td>(99.09, 99.43)</td><td>-</td></tr><tr><td>+ Abs</td><td>99.51</td><td>103</td><td>(99.38, 99.65)</td><td>-</td></tr><tr><td>most cases.</td><td/><td/><td/><td/></tr><tr><td colspan=\"5\">More accurate network is extended LeNet architecture -Lenet+Conv120+Abs,</td></tr><tr><td colspan=\"5\">created by adding Conv120 and AveragePooling layers to LeNet (it has 76226</td></tr><tr><td colspan=\"2\">parameters and is shown in Fig.</td><td/><td/><td/></tr></table>"
            }
        }
    }
}